gqla/GQLA.py
gqla/__init__.py
gqla/settings.py
gqla/Executor/Executor.py
gqla/Executor/__init__.py
gqla/GQLModel/GQLModel.py
gqla/GQLModel/__init__.py
gqla/GQLStorage/GQLStorage.py
gqla/GQLStorage/__init__.py
gqla/GQQStorage/GQQStorage.py
gqla/GQQStorage/__init__.py
gqla/GQQuery/GQQuery.py
gqla/GQQuery/__init__.py
gqla/GQQuery/Generator/Generator.py
gqla/GQQuery/Generator/__init__.py
gqla/VerticalStorage/VerticalStorage.py
gqla/VerticalStorage/__init__.py
gqla/abstracts/Executor.py
gqla/abstracts/GQGenerator.py
gqla/abstracts/GQLModel.py
gqla/abstracts/GQLStorage.py
gqla/abstracts/GQQStorage.py
gqla/abstracts/GQQery.py
gqla/abstracts/__init__.py
gqla/statics/__init__.py
gqla/statics/queries.py
gqla-1.1.2.dist-info/LICENSE
gqla-1.1.2.dist-info/METADATA
gqla-1.1.2.dist-info/WHEEL
gqla-1.1.2.dist-info/top_level.txt
gqla-1.1.2.dist-info/RECORD
