Metadata-Version: 2.1
Name: gqla
Version: 1.1.2
Summary: A module used to generate querry statements and perform data fetching via GraphQL
Home-page: https://github.com/Alenstoir/GQLA
Author: Alexey Kuzin
Author-email: alenstoir@yandex.ru
License: MIT License
Platform: UNKNOWN
Classifier: Programming Language :: Python :: 3
Classifier: License :: OSI Approved :: MIT License
Classifier: Operating System :: OS Independent
Requires: a
Requires: i
Requires: o
Requires: h
Requires: t
Requires: t
Requires: p
Requires-Python: >=3.5
